llm_classifiers/__init__.py
llm_classifiers/dummy_method.py
llm_classifiers-0.1.0.dist-info/METADATA
llm_classifiers-0.1.0.dist-info/WHEEL
llm_classifiers-0.1.0.dist-info/licenses/LICENSE
llm_classifiers-0.1.0.dist-info/RECORD
