Metadata-Version: 2.4
Name: llm-classifiers
Version: 0.1.0
Summary: Framework to build production-grade LLM-based classifiers
Author-email: Mads Møller <mads.moeller@outlook.com>
License-File: LICENSE
Requires-Python: >=3.11
Requires-Dist: pydantic-ai>=0.0.41
Requires-Dist: pydantic>=2.10.6
